python_roku-3.1.4.dist-info/DESCRIPTION.rst
python_roku-3.1.4.dist-info/METADATA
python_roku-3.1.4.dist-info/RECORD
python_roku-3.1.4.dist-info/WHEEL
python_roku-3.1.4.dist-info/metadata.json
python_roku-3.1.4.dist-info/top_level.txt
roku/__init__.py
roku/core.py
roku/discovery.py
roku/proxy.py
roku/server.py
roku/tests.py
roku/emulator/__init__.py
roku/emulator/core.py
