Metadata-Version: 2.0
Name: python-roku
Version: 3.1.4
Summary: Client for the Roku media player
Home-page: https://github.com/bah2830/python-roku
Author: Jeremy Carbaugh
Author-email: jcarbaugh@gmail.com
License: BSD License
Platform: any
Classifier: Development Status :: 4 - Beta
Classifier: Intended Audience :: Developers
Classifier: License :: OSI Approved :: BSD License
Classifier: Natural Language :: English
Classifier: Operating System :: OS Independent
Classifier: Programming Language :: Python
Requires-Dist: requests (>=2.1.0)
Requires-Dist: six
